nyuki/__init__.py
nyuki/commands.py
nyuki/config.py
nyuki/debugging.py
nyuki/logs.py
nyuki/nyuki.py
nyuki/services.py
nyuki/api/__init__.py
nyuki/api/api.py
nyuki/api/bus.py
nyuki/api/config.py
nyuki/bus/__init__.py
nyuki/bus/mqtt.py
nyuki/utils/__init__.py
nyuki/utils/dtutils.py
nyuki/utils/evaluate.py
nyuki/utils/serialize.py
nyuki/utils/transform.py
nyuki/workflow/__init__.py
nyuki/workflow/tukio.py
nyuki/workflow/validation.py
nyuki/workflow/workflow.py
nyuki/workflow/api/__init__.py
nyuki/workflow/api/factory.py
nyuki/workflow/api/instances.py
nyuki/workflow/api/templates.py
nyuki/workflow/api/vars.py
nyuki/workflow/db/__init__.py
nyuki/workflow/db/data_processing.py
nyuki/workflow/db/metadata.py
nyuki/workflow/db/storage.py
nyuki/workflow/db/task_instances.py
nyuki/workflow/db/task_templates.py
nyuki/workflow/db/triggers.py
nyuki/workflow/db/workflow_instances.py
nyuki/workflow/db/workflow_templates.py
nyuki/workflow/db/migrations/0001_structure_change.py
nyuki/workflow/db/migrations/__init__.py
nyuki/workflow/db/utils/__init__.py
nyuki/workflow/db/utils/indexes.py
nyuki/workflow/tasks/__init__.py
nyuki/workflow/tasks/factory.py
nyuki/workflow/tasks/python_script.py
nyuki/workflow/tasks/report.py
nyuki/workflow/tasks/sleep.py
nyuki/workflow/tasks/task_selector.py
nyuki/workflow/tasks/trigger_workflow.py
nyuki/workflow/tasks/utils/__init__.py
nyuki/workflow/tasks/utils/placeholder_mapper.py
nyuki/workflow/tasks/utils/runtime.py
nyuki/workflow/tasks/utils/selectors.py
nyuki/workflow/tasks/utils/uri.py
nyuki-0.56.0.dist-info/LICENSE
nyuki-0.56.0.dist-info/LICENSE-3RD-PARTY
nyuki-0.56.0.dist-info/METADATA
nyuki-0.56.0.dist-info/WHEEL
nyuki-0.56.0.dist-info/top_level.txt
nyuki-0.56.0.dist-info/RECORD
