Metadata-Version: 2.1
Name: nyuki
Version: 0.56.0
Summary: Base library to create microservices with MQTT and HTTP REST API.
Home-page: http://www.enovacom.fr
Author: Enovacom Surycat
Author-email: rand@surycat.com
License: Apache 2.0
Platform: UNKNOWN
Classifier: Development Status :: 2 - Pre-Alpha
Classifier: Intended Audience :: Developers
Classifier: Natural Language :: English
Classifier: License :: OSI Approved :: Apache Software License
Classifier: Programming Language :: Python :: 3.6
Classifier: Programming Language :: Python :: 3 :: Only
Requires-Dist: aiohttp (==3.5.4)
Requires-Dist: async-timeout (==3.0.1)
Requires-Dist: attrs (==19.1.0)
Requires-Dist: chardet (==3.0.4)
Requires-Dist: docopt (==0.6.2)
Requires-Dist: hbmqtt (==0.9.5)
Requires-Dist: idna-ssl (==1.1.0)
Requires-Dist: idna (==2.8)
Requires-Dist: jsonschema (==2.6.0)
Requires-Dist: motor (==2.0.0)
Requires-Dist: multidict (==4.5.2)
Requires-Dist: passlib (==1.7.1)
Requires-Dist: pijon (==0.1.2)
Requires-Dist: pymongo (==3.8.0)
Requires-Dist: pyyaml (==5.1)
Requires-Dist: six (==1.12.0)
Requires-Dist: transitions (==0.6.9)
Requires-Dist: tukio (==0.16.0)
Requires-Dist: typing-extensions (==3.7.2)
Requires-Dist: websockets (==7.0)
Requires-Dist: yarl (==1.3.0)
